{
  "sessio_id": "friedrich-nietzsche-humà,-massa-humà-2026-03-17",
  "obra": {
    "autor": "Friedrich Nietzsche",
    "titol": "Humà, massa humà",
    "llengua": "alemany"
  },
  "timestamps": {
    "inici": "2026-03-17T05:55:23.429095",
    "ultima_activitat": "2026-03-17T07:47:08.181823"
  },
  "fase_actual": "traduccio",
  "fases_completades": [
    "investigacio",
    "glossari",
    "chunking",
    "traduccio",
    "anotacio"
  ],
  "chunks": {
    "total": 57,
    "completats": [
      "chunk_1",
      "chunk_2",
      "chunk_3",
      "chunk_4",
      "chunk_5",
      "chunk_6",
      "chunk_7",
      "chunk_8",
      "chunk_9",
      "chunk_10",
      "chunk_11",
      "chunk_12",
      "chunk_13",
      "chunk_14",
      "chunk_15",
      "chunk_16",
      "chunk_17",
      "chunk_18",
      "chunk_19",
      "chunk_20",
      "chunk_21",
      "chunk_22",
      "chunk_23",
      "chunk_24",
      "chunk_25",
      "chunk_26",
      "chunk_27",
      "chunk_28",
      "chunk_29",
      "chunk_30",
      "chunk_31",
      "chunk_32",
      "chunk_33",
      "chunk_34",
      "chunk_35",
      "chunk_36",
      "chunk_37",
      "chunk_38",
      "chunk_39",
      "chunk_40",
      "chunk_41",
      "chunk_42",
      "chunk_43",
      "chunk_44",
      "chunk_45",
      "chunk_46",
      "chunk_47",
      "chunk_48",
      "chunk_49",
      "chunk_50",
      "chunk_51",
      "chunk_52",
      "chunk_53",
      "chunk_54",
      "chunk_55",
      "chunk_56",
      "chunk_57",
      "chunk_58",
      "chunk_59",
      "chunk_60",
      "chunk_61",
      "chunk_62",
      "chunk_63",
      "chunk_64",
      "chunk_65",
      "chunk_66",
      "chunk_67",
      "chunk_68",
      "chunk_69",
      "chunk_70",
      "chunk_71",
      "chunk_72"
    ],
    "en_curs": "chunk_73",
    "pendents": []
  },
  "metriques": {
    "qualitat_mitjana": 1.26,
    "temps_total_min": 0.0
  },
  "errors": [
    "[05:57:38] Error chunk 1: [Errno 32] Broken pipe",
    "[05:57:38] Error chunk 2: [Errno 32] Broken pipe",
    "[05:57:38] Error chunk 3: [Errno 32] Broken pipe",
    "[05:57:38] Error chunk 4: [Errno 32] Broken pipe",
    "[05:57:38] Error chunk 5: [Errno 32] Broken pipe",
    "[05:57:38] Error chunk 6: [Errno 32] Broken pipe",
    "[05:57:38] Error chunk 7: [Errno 32] Broken pipe",
    "[05:57:38] Error chunk 8: [Errno 32] Broken pipe",
    "[05:57:38] Error chunk 9: [Errno 32] Broken pipe",
    "[05:57:38] Error chunk 10: [Errno 32] Broken pipe",
    "[05:57:38] Error chunk 11: [Errno 32] Broken pipe",
    "[05:57:38] Error chunk 12: [Errno 32] Broken pipe",
    "[05:57:38] Error chunk 13: [Errno 32] Broken pipe",
    "[05:57:38] Error chunk 14: [Errno 32] Broken pipe",
    "[05:57:38] Error chunk 15: [Errno 32] Broken pipe",
    "[05:57:38] Error chunk 16: [Errno 32] Broken pipe",
    "[05:57:38] Error chunk 17: [Errno 32] Broken pipe",
    "[05:57:38] Error chunk 18: [Errno 32] Broken pipe",
    "[05:57:38] Error chunk 19: [Errno 32] Broken pipe",
    "[05:57:38] Error chunk 20: [Errno 32] Broken pipe",
    "[05:57:38] Error chunk 21: [Errno 32] Broken pipe",
    "[05:57:38] Error chunk 22: [Errno 32] Broken pipe",
    "[05:57:38] Error chunk 23: [Errno 32] Broken pipe",
    "[05:57:38] Error chunk 24: [Errno 32] Broken pipe",
    "[05:57:38] Error chunk 25: [Errno 32] Broken pipe",
    "[05:57:38] Error chunk 26: [Errno 32] Broken pipe",
    "[05:57:38] Error chunk 27: [Errno 32] Broken pipe",
    "[05:57:38] Error chunk 28: [Errno 32] Broken pipe",
    "[05:57:38] Error chunk 29: [Errno 32] Broken pipe",
    "[05:57:38] Error chunk 30: [Errno 32] Broken pipe",
    "[05:57:38] Error chunk 31: [Errno 32] Broken pipe",
    "[05:57:38] Error chunk 32: [Errno 32] Broken pipe",
    "[05:57:38] Error chunk 33: [Errno 32] Broken pipe",
    "[05:57:38] Error chunk 34: [Errno 32] Broken pipe",
    "[05:57:38] Error chunk 35: [Errno 32] Broken pipe",
    "[05:57:38] Error chunk 36: [Errno 32] Broken pipe",
    "[05:57:38] Error chunk 37: [Errno 32] Broken pipe",
    "[05:57:38] Error chunk 38: [Errno 32] Broken pipe",
    "[05:57:38] Error chunk 39: [Errno 32] Broken pipe",
    "[05:57:38] Error chunk 40: [Errno 32] Broken pipe",
    "[05:57:38] Error chunk 41: [Errno 32] Broken pipe",
    "[05:57:38] Error chunk 42: [Errno 32] Broken pipe",
    "[05:57:38] Error chunk 43: [Errno 32] Broken pipe",
    "[05:57:38] Error chunk 44: [Errno 32] Broken pipe",
    "[05:57:38] Error chunk 45: [Errno 32] Broken pipe",
    "[05:57:38] Error chunk 46: [Errno 32] Broken pipe",
    "[05:57:38] Error chunk 47: [Errno 32] Broken pipe",
    "[05:57:38] Error chunk 48: [Errno 32] Broken pipe",
    "[05:57:38] Error chunk 49: [Errno 32] Broken pipe",
    "[05:57:38] Error chunk 50: [Errno 32] Broken pipe",
    "[05:57:38] Error chunk 51: [Errno 32] Broken pipe",
    "[05:57:38] Error chunk 52: [Errno 32] Broken pipe",
    "[05:57:38] Error chunk 53: [Errno 32] Broken pipe",
    "[05:57:38] Error chunk 54: [Errno 32] Broken pipe",
    "[05:57:38] Error chunk 55: [Errno 32] Broken pipe",
    "[05:57:38] Error chunk 56: [Errno 32] Broken pipe",
    "[05:57:38] Error chunk 57: [Errno 32] Broken pipe",
    "[05:57:38] Error fatal: [Errno 32] Broken pipe",
    "[06:01:22] Error chunk 2: El CLI ha retornat una resposta buida (sense contingut)",
    "[06:04:41] Error chunk 4: El CLI ha retornat una resposta buida (sense contingut)",
    "[06:08:26] Error chunk 6: El CLI ha retornat una resposta buida (sense contingut)",
    "[06:10:03] Error chunk 7: El CLI ha retornat una resposta buida (sense contingut)",
    "[06:10:37] Error chunk 8: El CLI ha retornat una resposta buida (sense contingut)",
    "[06:14:13] Error chunk 10: El CLI ha retornat una resposta buida (sense contingut)",
    "[06:15:32] Error chunk 11: El CLI ha retornat una resposta buida (sense contingut)",
    "[06:17:05] Error chunk 12: El CLI ha retornat una resposta buida (sense contingut)",
    "[06:20:33] Error chunk 14: El CLI ha retornat una resposta buida (sense contingut)",
    "[06:23:48] Error chunk 16: El CLI ha retornat una resposta buida (sense contingut)",
    "[06:25:10] Error chunk 17: El CLI ha retornat una resposta buida (sense contingut)",
    "[06:26:37] Error chunk 18: El CLI ha retornat una resposta buida (sense contingut)",
    "[06:33:20] Error chunk 21: El CLI ha retornat una resposta buida (sense contingut)",
    "[06:35:16] Error chunk 22: El CLI ha retornat una resposta buida (sense contingut)",
    "[06:44:02] Error chunk 26: El CLI ha retornat una resposta buida (sense contingut)",
    "[06:44:46] Error chunk 27: El CLI ha retornat una resposta buida (sense contingut)",
    "[06:45:26] Error chunk 28: El CLI ha retornat una resposta buida (sense contingut)",
    "[06:47:04] Error chunk 29: El CLI ha retornat una resposta buida (sense contingut)",
    "[06:50:18] Error chunk 31: El CLI ha retornat una resposta buida (sense contingut)",
    "[06:50:57] Error chunk 32: El CLI ha retornat una resposta buida (sense contingut)",
    "[06:52:06] Error chunk 33: El CLI ha retornat una resposta buida (sense contingut)",
    "[06:52:44] Error chunk 34: El CLI ha retornat una resposta buida (sense contingut)",
    "[06:56:22] Error chunk 36: El CLI ha retornat una resposta buida (sense contingut)",
    "[07:00:27] Error chunk 38: El CLI ha retornat una resposta buida (sense contingut)",
    "[07:02:41] Error chunk 40: El CLI ha retornat una resposta buida (sense contingut)",
    "[07:09:11] Error chunk 43: El CLI ha retornat una resposta buida (sense contingut)",
    "[07:10:01] Error chunk 44: El CLI ha retornat una resposta buida (sense contingut)",
    "[07:10:44] Error chunk 45: El CLI ha retornat una resposta buida (sense contingut)",
    "[07:11:20] Error chunk 46: El CLI ha retornat una resposta buida (sense contingut)",
    "[07:18:05] Error chunk 49: El CLI ha retornat una resposta buida (sense contingut)",
    "[07:18:54] Error chunk 50: El CLI ha retornat una resposta buida (sense contingut)",
    "[07:19:38] Error chunk 51: El CLI ha retornat una resposta buida (sense contingut)",
    "[07:25:43] Error chunk 54: El CLI ha retornat una resposta buida (sense contingut)",
    "[07:26:27] Error chunk 55: El CLI ha retornat una resposta buida (sense contingut)",
    "[07:27:07] Error chunk 56: El CLI ha retornat una resposta buida (sense contingut)",
    "[07:27:49] Error chunk 57: El CLI ha retornat una resposta buida (sense contingut)",
    "[07:28:30] Error chunk 58: El CLI ha retornat una resposta buida (sense contingut)",
    "[07:30:01] Error chunk 59: El CLI ha retornat una resposta buida (sense contingut)",
    "[07:30:40] Error chunk 60: El CLI ha retornat una resposta buida (sense contingut)",
    "[07:31:27] Error chunk 61: El CLI ha retornat una resposta buida (sense contingut)",
    "[07:31:57] Error chunk 62: El CLI ha retornat una resposta buida (sense contingut)",
    "[07:33:11] Error chunk 63: El CLI ha retornat una resposta buida (sense contingut)",
    "[07:33:48] Error chunk 64: El CLI ha retornat una resposta buida (sense contingut)",
    "[07:34:54] Error chunk 65: El CLI ha retornat una resposta buida (sense contingut)",
    "[07:35:30] Error chunk 66: El CLI ha retornat una resposta buida (sense contingut)",
    "[07:41:46] Error chunk 69: El CLI ha retornat una resposta buida (sense contingut)",
    "[07:43:21] Error chunk 70: El CLI ha retornat una resposta buida (sense contingut)",
    "[07:47:08] Error chunk 72: El CLI ha retornat una resposta buida (sense contingut)"
  ],
  "warnings": [
    "[05:57:04] Error glossari: El CLI ha retornat una resposta buida (sense contingut)",
    "[05:57:38] Error anotació: [Errno 32] Broken pipe"
  ]
}